{
  "equations": "Linear Equations",
  "vectors": "Vectors",
  "matrices": "Matrices",
  "rank": "Linear Independence and Rank",
  "inverse": "Matrix Inverses",
  "transformations": "Linear Transformations",
  "gaussianElimination": "Gaussian Elimination",
  "vectorMatrixSpaces": "Vector and Matrix Spaces",
  "determinants": "Determinants",
  "cramerRule": "Cramer's Rule",
  "qrDecomposition": "QR Decomposition",
  "eigenvaluesEigenvectors": "Eigenvalues and Eigenvectors",
  "svd": "SVD - Singular Value Decomposition",
  "moorePenrose": "Moore-Penrose Pseudoinverse",
  "quadraticForms": "Quadratic Forms",
  "definiteness": "Definiteness of a Matrix",
  "pca": "PCA - Principal Component Analysis",
  "hadamardProduct": "Hadamard Product",
  "crossProduct": "Cross Product",
  "broadcasting": "Broadcasting"
}
